AUTHORS.rst
CONTRIBUTING.rst
HISTORY.rst
LICENSE
MANIFEST.in
README.rst
setup.cfg
setup.py
egg/__init__.py
egg/egg.py
egg.egg-info/PKG-INFO
egg.egg-info/SOURCES.txt
egg.egg-info/dependency_links.txt
egg.egg-info/not-zip-safe
egg.egg-info/top_level.txt