Metadata-Version: 1.1
Name: egg
Version: 0.1.0
Summary: This is a lonely egg.
Home-page: https://github.com/rgbkrk/egg
Author: Kyle Kelley
Author-email: rgbkrk@gmail.com
License: BSD
Keywords: egg
Platform: UNKNOWN
Classifier: Development Status :: 2 - Pre-Alpha
Classifier: Intended Audience :: Developers
Classifier: License :: OSI Approved :: BSD License
Classifier: Natural Language :: English
Classifier: Programming Language :: Python :: 2
Classifier: Programming Language :: Python :: 2.6
Classifier: Programming Language :: Python :: 2.7
Classifier: Programming Language :: Python :: 3
Classifier: Programming Language :: Python :: 3.3
